lcd_i2c/__init__.py
lcd_i2c/constants.py
lcd_i2c/custom_chars/__init__.py
lcd_i2c/custom_chars/main.py
lcd_i2c/custom_chars/others.py
lcd_i2c/custom_chars/roms/A00.py
lcd_i2c/custom_chars/roms/A02.py
lcd_i2c/helpers/delay.py
lcd_i2c/helpers/local_testing.py
lcd_i2c/main.py
lcd_i2c-0.2.3.dist-info/WHEEL
lcd_i2c-0.2.3.dist-info/METADATA
lcd_i2c-0.2.3.dist-info/RECORD
